bookmarks_converter/__init__.py
bookmarks_converter/__main__.py
bookmarks_converter/cli.py
bookmarks_converter/converters/__init__.py
bookmarks_converter/converters/bookmarkie.py
bookmarks_converter/converters/chrome.py
bookmarks_converter/converters/converter.py
bookmarks_converter/converters/firefox.py
bookmarks_converter/formats.py
bookmarks_converter/models.py
bookmarks_converter/util.py
bookmarks_converter-1.0.2.dist-info/METADATA
bookmarks_converter-1.0.2.dist-info/WHEEL
bookmarks_converter-1.0.2.dist-info/entry_points.txt
bookmarks_converter-1.0.2.dist-info/licenses/LICENSE
bookmarks_converter-1.0.2.dist-info/RECORD
