Metadata-Version: 2.4
Name: bookmarks-converter
Version: 1.0.2
Summary: Convert browser bookmarks files.
License: MIT
License-File: LICENSE
Keywords: bookmarks,bookmarks converter,bookmarks-converter,bookmarks-parser,bookmarks parser
Author: Adam Saleh
Author-email: radam9@gmail.com
Requires-Python: >=3.11,<4.0
Classifier: License :: OSI Approved :: MIT License
Classifier: Programming Language :: Python :: 3
Classifier: Programming Language :: Python :: 3.11
Classifier: Programming Language :: Python :: 3.12
Classifier: Programming Language :: Python :: 3.13
Classifier: Programming Language :: Python :: 3.14
Classifier: Topic :: Utilities
Requires-Dist: SQLAlchemy (>=2.0.0,<3.0.0)
Requires-Dist: beautifulsoup4 (>=4.10.0,<5.0.0)
Project-URL: Homepage, https://github.com/radam9/bookmarks-converter
Project-URL: Repository, https://github.com/radam9/bookmarks-converter
